<?xml version="1.0" encoding="UTF-8"?>

<mule xmlns:ee="http://www.mulesoft.org/schema/mule/ee/core" xmlns="http://www.mulesoft.org/schema/mule/core"
      xmlns:doc="http://www.mulesoft.org/schema/mule/documentation"
      xmlns:xsi="http://www.w3.org/2001/XMLSchema-instance" xsi:schemaLocation="http://www.mulesoft.org/schema/mule/core http://www.mulesoft.org/schema/mule/core/current/mule.xsd
http://www.mulesoft.org/schema/mule/ee/core http://www.mulesoft.org/schema/mule/ee/core/current/mule-ee.xsd">
    <sub-flow name="error-handling-Sub_Flow" doc:id="3b4e3606-24c8-45a0-8b78-c2befbc6224e" >
        <ee:transform doc:name="Prepare Exception Response" doc:id="546b6ba6-2c0f-47f3-b814-4378f6a4541f" >
            <ee:message >
                <ee:set-payload ><![CDATA[%dw 2.0
output application/json
---
{
	statusCode: vars.httpStatus,
  	error: {
  		"type": error.errorType.namespace ++ ":" ++ error.errorType.identifier,
  		message: error.description default "Unhandled Exception"
  	}
}]]></ee:set-payload>
            </ee:message>
            <ee:variables >
            </ee:variables>
        </ee:transform>
    </sub-flow>
</mule>
